CHANGES.rst
CONTRIBUTORS.rst
DEVELOP.rst
LICENSE.GPL
LICENSE.rst
MANIFEST.in
README.rst
setup.py
docs/index.rst
src/plone/__init__.py
src/plone.app.jsonfield.egg-info/PKG-INFO
src/plone.app.jsonfield.egg-info/SOURCES.txt
src/plone.app.jsonfield.egg-info/dependency_links.txt
src/plone.app.jsonfield.egg-info/entry_points.txt
src/plone.app.jsonfield.egg-info/namespace_packages.txt
src/plone.app.jsonfield.egg-info/not-zip-safe
src/plone.app.jsonfield.egg-info/requires.txt
src/plone.app.jsonfield.egg-info/top_level.txt
src/plone/app/__init__.py
src/plone/app/jsonfield/__init__.py
src/plone/app/jsonfield/compat.py
src/plone/app/jsonfield/configure.zcml
src/plone/app/jsonfield/deserializer.py
src/plone/app/jsonfield/deserializer.zcml
src/plone/app/jsonfield/field.py
src/plone/app/jsonfield/handler.py
src/plone/app/jsonfield/handler.zcml
src/plone/app/jsonfield/helpers.py
src/plone/app/jsonfield/interfaces.py
src/plone/app/jsonfield/marshaler.py
src/plone/app/jsonfield/marshaler.zcml
src/plone/app/jsonfield/permissions.zcml
src/plone/app/jsonfield/schemaeditor.py
src/plone/app/jsonfield/schemaeditor.zcml
src/plone/app/jsonfield/serializer.py
src/plone/app/jsonfield/serializer.zcml
src/plone/app/jsonfield/setuphandlers.py
src/plone/app/jsonfield/testing.py
src/plone/app/jsonfield/upgrades.py
src/plone/app/jsonfield/upgrades.zcml
src/plone/app/jsonfield/value.py
src/plone/app/jsonfield/widget.py
src/plone/app/jsonfield/widget.zcml
src/plone/app/jsonfield/browser/__init__.py
src/plone/app/jsonfield/browser/configure.zcml
src/plone/app/jsonfield/browser/overrides/.gitkeep
src/plone/app/jsonfield/browser/static/.gitkeep
src/plone/app/jsonfield/locales/plone.app.fhirfield.pot
src/plone/app/jsonfield/locales/update.sh
src/plone/app/jsonfield/profiles/default/metadata.xml
src/plone/app/jsonfield/profiles/default/registry.xml
src/plone/app/jsonfield/profiles/default/rolemap.xml
src/plone/app/jsonfield/profiles/testing/types.xml
src/plone/app/jsonfield/profiles/testing/types/TestToken.xml
src/plone/app/jsonfield/profiles/uninstall/browserlayer.xml
src/plone/app/jsonfield/templates/widget/display.pt
src/plone/app/jsonfield/templates/widget/hidden.pt
src/plone/app/jsonfield/templates/widget/input.pt
src/plone/app/jsonfield/templates/widget/textarea_display.pt
src/plone/app/jsonfield/tests/__init__.py
src/plone/app/jsonfield/tests/test_deserializer.py
