Metadata-Version: 1.1
Name: plone.app.jsonfield
Version: 1.0.0a3
Summary: JSON field for Plone
Home-page: https://pypi.python.org/pypi/plone.app.jsonfield
Author: Md Nazrul Islam
Author-email: email2nazrul@gmail.com
License: GPL version 2
Keywords: Python Plone JSON
Platform: UNKNOWN
Classifier: Development Status :: 3 - Alpha
Classifier: Environment :: Web Environment
Classifier: Framework :: Plone
Classifier: Framework :: Plone :: 4.3
Classifier: Framework :: Plone :: 5.0
Classifier: Framework :: Plone :: 5.1
Classifier: Programming Language :: Python
Classifier: Programming Language :: Python :: 2.7
Classifier: Programming Language :: Python :: 3
Classifier: Operating System :: OS Independent
Classifier: License :: OSI Approved :: GNU General Public License v2 (GPLv2)
